{
  "date": "2026-04-17",
  "generated_at": "2026-04-18T03:26:34Z",
  "symbols": {
    "BTCUSDT": {
      "open": "75122.22000000",
      "high": "78304.82000000",
      "low": "74568.28000000",
      "close": "77097.65000000",
      "volume": "43.03798000",
      "quote_volume": "3303666.30845280",
      "trades": 3041,
      "taker_buy_volume": "17.84660000",
      "change_pct": 2.6296,
      "candle_time": 1776384000000
    },
    "ETHUSDT": {
      "open": "2347.92000000",
      "high": "2464.14000000",
      "low": "2318.25000000",
      "close": "2419.93000000",
      "volume": "314.21460000",
      "quote_volume": "756912.25240500",
      "trades": 1774,
      "taker_buy_volume": "154.98620000",
      "change_pct": 3.067,
      "candle_time": 1776384000000
    },
    "SOLUSDT": {
      "open": "89.09000000",
      "high": "90.70000000",
      "low": "87.41000000",
      "close": "88.83000000",
      "volume": "3396.43400000",
      "quote_volume": "302027.08741000",
      "trades": 773,
      "taker_buy_volume": "1834.66900000",
      "change_pct": -0.2918,
      "candle_time": 1776384000000
    },
    "XRPUSDT": {
      "open": "1.45320000",
      "high": "1.51020000",
      "low": "1.42350000",
      "close": "1.47620000",
      "volume": "413261.80000000",
      "quote_volume": "608274.11002000",
      "trades": 1200,
      "taker_buy_volume": "307399.60000000",
      "change_pct": 1.5827,
      "candle_time": 1776384000000
    },
    "BNBUSDT": {
      "open": "635.68000000",
      "high": "645.69000000",
      "low": "627.25000000",
      "close": "642.66000000",
      "volume": "83.99400000",
      "quote_volume": "53819.74487000",
      "trades": 417,
      "taker_buy_volume": "61.56800000",
      "change_pct": 1.098,
      "candle_time": 1776384000000
    }
  }
}