[{"timestamp":"2026-04-12T16:47:12Z","unix":1776012432,"oi":{}},{"timestamp":"2026-04-12T16:59:36Z","unix":1776013176,"oi":{}},{"timestamp":"2026-04-12T17:01:13Z","unix":1776013273,"oi":{}},{"timestamp":"2026-04-12T17:04:09Z","unix":1776013449,"oi":{}},{"timestamp":"2026-04-13T06:09:54Z","unix":1776060594,"oi":{"BTCUSDT":"0","ETHUSDT":"0","SOLUSDT":"0","XRPUSDT":"0","BNBUSDT":"0"},"oi_value":{"BTCUSDT":"0","ETHUSDT":"0","SOLUSDT":"0","XRPUSDT":"0","BNBUSDT":"0"}},{"timestamp":"2026-04-13T06:26:54Z","unix":1776061614,"oi":{"BTCUSDT":"0","ETHUSDT":"0","SOLUSDT":"0","XRPUSDT":"0","BNBUSDT":"0"},"oi_value":{"BTCUSDT":"0","ETHUSDT":"0","SOLUSDT":"0","XRPUSDT":"0","BNBUSDT":"0"}},{"timestamp":"2026-04-13T07:19:10Z","unix":1776064750,"oi":{"BTCUSDT":"0","ETHUSDT":"0","SOLUSDT":"0","XRPUSDT":"0","BNBUSDT":"0"},"oi_value":{"BTCUSDT":"0","ETHUSDT":"0","SOLUSDT":"0","XRPUSDT":"0","BNBUSDT":"0"}},{"timestamp":"2026-04-13T07:23:53Z","unix":1776065033,"oi":{"BTCUSDT":"0","ETHUSDT":"0","SOLUSDT":"0","XRPUSDT":"0","BNBUSDT":"0"},"oi_value":{"BTCUSDT":"0","ETHUSDT":"0","SOLUSDT":"0","XRPUSDT":"0","BNBUSDT":"0"}},{"timestamp":"2026-04-13T09:16:06Z","unix":1776071766,"oi":{"BTCUSDT":"0","ETHUSDT":"0","SOLUSDT":"0","XRPUSDT":"0","BNBUSDT":"0"},"oi_value":{"BTCUSDT":"0","ETHUSDT":"0","SOLUSDT":"0","XRPUSDT":"0","BNBUSDT":"0"}},{"timestamp":"2026-04-13T10:57:26Z","unix":1776077846,"oi":{"BTCUSDT":"0","ETHUSDT":"0","SOLUSDT":"0","XRPUSDT":"0","BNBUSDT":"0"},"oi_value":{"BTCUSDT":"0","ETHUSDT":"0","SOLUSDT":"0","XRPUSDT":"0","BNBUSDT":"0"}},{"timestamp":"2026-04-13T12:02:15Z","unix":1776081735,"oi":{"BTCUSDT":"0","ETHUSDT":"0","SOLUSDT":"0","XRPUSDT":"0","BNBUSDT":"0"},"oi_value":{"BTCUSDT":"0","ETHUSDT":"0","SOLUSDT":"0","XRPUSDT":"0","BNBUSDT":"0"}},{"timestamp":"2026-04-13T12:37:36Z","unix":1776083856,"oi":{"BTCUSDT":"0","ETHUSDT":"0","SOLUSDT":"0","XRPUSDT":"0","BNBUSDT":"0"},"oi_value":{"BTCUSDT":"0","ETHUSDT":"0","SOLUSDT":"0","XRPUSDT":"0","BNBUSDT":"0"}},{"timestamp":"2026-04-13T12:51:58Z","unix":1776084718,"oi":{"BTCUSDT":"0","ETHUSDT":"0","SOLUSDT":"0","XRPUSDT":"0","BNBUSDT":"0"},"oi_value":{"BTCUSDT":"0","ETHUSDT":"0","SOLUSDT":"0","XRPUSDT":"0","BNBUSDT":"0"}},{"timestamp":"2026-04-13T14:03:37Z","unix":1776089017,"oi":{"BTCUSDT":"0","ETHUSDT":"0","SOLUSDT":"0","XRPUSDT":"0","BNBUSDT":"0"},"oi_value":{"BTCUSDT":"0","ETHUSDT":"0","SOLUSDT":"0","XRPUSDT":"0","BNBUSDT":"0"}},{"timestamp":"2026-04-13T15:24:58Z","unix":1776093898,"oi":{"BTCUSDT":"0","ETHUSDT":"0","SOLUSDT":"0","XRPUSDT":"0","BNBUSDT":"0"},"oi_value":{"BTCUSDT":"0","ETHUSDT":"0","SOLUSDT":"0","XRPUSDT":"0","BNBUSDT":"0"}},{"timestamp":"2026-04-13T16:41:17Z","unix":1776098477,"oi":{"BTCUSDT":"0","ETHUSDT":"0","SOLUSDT":"0","XRPUSDT":"0","BNBUSDT":"0"},"oi_value":{"BTCUSDT":"0","ETHUSDT":"0","SOLUSDT":"0","XRPUSDT":"0","BNBUSDT":"0"}},{"timestamp":"2026-04-13T17:42:13Z","unix":1776102133,"oi":{"BTCUSDT":"0","ETHUSDT":"0","SOLUSDT":"0","XRPUSDT":"0","BNBUSDT":"0"},"oi_value":{"BTCUSDT":"0","ETHUSDT":"0","SOLUSDT":"0","XRPUSDT":"0","BNBUSDT":"0"}},{"timestamp":"2026-04-13T18:49:30Z","unix":1776106170,"oi":{"BTCUSDT":"0","ETHUSDT":"0","SOLUSDT":"0","XRPUSDT":"0","BNBUSDT":"0"},"oi_value":{"BTCUSDT":"0","ETHUSDT":"0","SOLUSDT":"0","XRPUSDT":"0","BNBUSDT":"0"}},{"timestamp":"2026-04-13T19:56:29Z","unix":1776110189,"oi":{"BTCUSDT":"0","ETHUSDT":"0","SOLUSDT":"0","XRPUSDT":"0","BNBUSDT":"0"},"oi_value":{"BTCUSDT":"0","ETHUSDT":"0","SOLUSDT":"0","XRPUSDT":"0","BNBUSDT":"0"}},{"timestamp":"2026-04-13T20:51:31Z","unix":1776113491,"oi":{"BTCUSDT":"0","ETHUSDT":"0","SOLUSDT":"0","XRPUSDT":"0","BNBUSDT":"0"},"oi_value":{"BTCUSDT":"0","ETHUSDT":"0","SOLUSDT":"0","XRPUSDT":"0","BNBUSDT":"0"}},{"timestamp":"2026-04-13T21:35:37Z","unix":1776116137,"oi":{"BTCUSDT":"0","ETHUSDT":"0","SOLUSDT":"0","XRPUSDT":"0","BNBUSDT":"0"},"oi_value":{"BTCUSDT":"0","ETHUSDT":"0","SOLUSDT":"0","XRPUSDT":"0","BNBUSDT":"0"}},{"timestamp":"2026-04-13T22:26:57Z","unix":1776119217,"oi":{"BTCUSDT":"0","ETHUSDT":"0","SOLUSDT":"0","XRPUSDT":"0","BNBUSDT":"0"},"oi_value":{"BTCUSDT":"0","ETHUSDT":"0","SOLUSDT":"0","XRPUSDT":"0","BNBUSDT":"0"}},{"timestamp":"2026-04-13T23:10:27Z","unix":1776121827,"oi":{"BTCUSDT":"0","ETHUSDT":"0","SOLUSDT":"0","XRPUSDT":"0","BNBUSDT":"0"},"oi_value":{"BTCUSDT":"0","ETHUSDT":"0","SOLUSDT":"0","XRPUSDT":"0","BNBUSDT":"0"}},{"timestamp":"2026-04-13T23:58:14Z","unix":1776124694,"oi":{"BTCUSDT":"0","ETHUSDT":"0","SOLUSDT":"0","XRPUSDT":"0","BNBUSDT":"0"},"oi_value":{"BTCUSDT":"0","ETHUSDT":"0","SOLUSDT":"0","XRPUSDT":"0","BNBUSDT":"0"}},{"timestamp":"2026-04-14T02:43:32Z","unix":1776134612,"oi":{"BTCUSDT":"0","ETHUSDT":"0","SOLUSDT":"0","XRPUSDT":"0","BNBUSDT":"0"},"oi_value":{"BTCUSDT":"0","ETHUSDT":"0","SOLUSDT":"0","XRPUSDT":"0","BNBUSDT":"0"}},{"timestamp":"2026-04-14T05:12:47Z","unix":1776143567,"oi":{"BTCUSDT":"0","ETHUSDT":"0","SOLUSDT":"0","XRPUSDT":"0","BNBUSDT":"0"},"oi_value":{"BTCUSDT":"0","ETHUSDT":"0","SOLUSDT":"0","XRPUSDT":"0","BNBUSDT":"0"}},{"timestamp":"2026-04-14T07:01:49Z","unix":1776150109,"oi":{"BTCUSDT":"0","ETHUSDT":"0","SOLUSDT":"0","XRPUSDT":"0","BNBUSDT":"0"},"oi_value":{"BTCUSDT":"0","ETHUSDT":"0","SOLUSDT":"0","XRPUSDT":"0","BNBUSDT":"0"}},{"timestamp":"2026-04-14T08:49:20Z","unix":1776156560,"oi":{"BTCUSDT":"0","ETHUSDT":"0","SOLUSDT":"0","XRPUSDT":"0","BNBUSDT":"0"},"oi_value":{"BTCUSDT":"0","ETHUSDT":"0","SOLUSDT":"0","XRPUSDT":"0","BNBUSDT":"0"}},{"timestamp":"2026-04-14T10:02:27Z","unix":1776160947,"oi":{"BTCUSDT":"0","ETHUSDT":"0","SOLUSDT":"0","XRPUSDT":"0","BNBUSDT":"0"},"oi_value":{"BTCUSDT":"0","ETHUSDT":"0","SOLUSDT":"0","XRPUSDT":"0","BNBUSDT":"0"}},{"timestamp":"2026-04-14T11:13:23Z","unix":1776165203,"oi":{"BTCUSDT":"0","ETHUSDT":"0","SOLUSDT":"0","XRPUSDT":"0","BNBUSDT":"0"},"oi_value":{"BTCUSDT":"0","ETHUSDT":"0","SOLUSDT":"0","XRPUSDT":"0","BNBUSDT":"0"}},{"timestamp":"2026-04-14T12:08:42Z","unix":1776168522,"oi":{"BTCUSDT":"0","ETHUSDT":"0","SOLUSDT":"0","XRPUSDT":"0","BNBUSDT":"0"},"oi_value":{"BTCUSDT":"0","ETHUSDT":"0","SOLUSDT":"0","XRPUSDT":"0","BNBUSDT":"0"}},{"timestamp":"2026-04-14T14:10:07Z","unix":1776175807,"oi":{"BTCUSDT":"0","ETHUSDT":"0","SOLUSDT":"0","XRPUSDT":"0","BNBUSDT":"0"},"oi_value":{"BTCUSDT":"0","ETHUSDT":"0","SOLUSDT":"0","XRPUSDT":"0","BNBUSDT":"0"}},{"timestamp":"2026-04-14T15:37:10Z","unix":1776181030,"oi":{"BTCUSDT":"0","ETHUSDT":"0","SOLUSDT":"0","XRPUSDT":"0","BNBUSDT":"0"},"oi_value":{"BTCUSDT":"0","ETHUSDT":"0","SOLUSDT":"0","XRPUSDT":"0","BNBUSDT":"0"}},{"timestamp":"2026-04-14T16:43:21Z","unix":1776185001,"oi":{"BTCUSDT":"0","ETHUSDT":"0","SOLUSDT":"0","XRPUSDT":"0","BNBUSDT":"0"},"oi_value":{"BTCUSDT":"0","ETHUSDT":"0","SOLUSDT":"0","XRPUSDT":"0","BNBUSDT":"0"}},{"timestamp":"2026-04-14T17:49:17Z","unix":1776188957,"oi":{"BTCUSDT":"0","ETHUSDT":"0","SOLUSDT":"0","XRPUSDT":"0","BNBUSDT":"0"},"oi_value":{"BTCUSDT":"0","ETHUSDT":"0","SOLUSDT":"0","XRPUSDT":"0","BNBUSDT":"0"}},{"timestamp":"2026-04-14T18:51:51Z","unix":1776192711,"oi":{"BTCUSDT":"0","ETHUSDT":"0","SOLUSDT":"0","XRPUSDT":"0","BNBUSDT":"0"},"oi_value":{"BTCUSDT":"0","ETHUSDT":"0","SOLUSDT":"0","XRPUSDT":"0","BNBUSDT":"0"}},{"timestamp":"2026-04-14T20:52:30Z","unix":1776199950,"oi":{"BTCUSDT":"0","ETHUSDT":"0","SOLUSDT":"0","XRPUSDT":"0","BNBUSDT":"0"},"oi_value":{"BTCUSDT":"0","ETHUSDT":"0","SOLUSDT":"0","XRPUSDT":"0","BNBUSDT":"0"}},{"timestamp":"2026-04-14T21:38:38Z","unix":1776202718,"oi":{"BTCUSDT":"0","ETHUSDT":"0","SOLUSDT":"0","XRPUSDT":"0","BNBUSDT":"0"},"oi_value":{"BTCUSDT":"0","ETHUSDT":"0","SOLUSDT":"0","XRPUSDT":"0","BNBUSDT":"0"}},{"timestamp":"2026-04-14T22:28:12Z","unix":1776205692,"oi":{"BTCUSDT":"0","ETHUSDT":"0","SOLUSDT":"0","XRPUSDT":"0","BNBUSDT":"0"},"oi_value":{"BTCUSDT":"0","ETHUSDT":"0","SOLUSDT":"0","XRPUSDT":"0","BNBUSDT":"0"}},{"timestamp":"2026-04-14T23:12:34Z","unix":1776208354,"oi":{"BTCUSDT":"0","ETHUSDT":"0","SOLUSDT":"0","XRPUSDT":"0","BNBUSDT":"0"},"oi_value":{"BTCUSDT":"0","ETHUSDT":"0","SOLUSDT":"0","XRPUSDT":"0","BNBUSDT":"0"}},{"timestamp":"2026-04-14T23:59:59Z","unix":1776211199,"oi":{"BTCUSDT":"0","ETHUSDT":"0","SOLUSDT":"0","XRPUSDT":"0","BNBUSDT":"0"},"oi_value":{"BTCUSDT":"0","ETHUSDT":"0","SOLUSDT":"0","XRPUSDT":"0","BNBUSDT":"0"}},{"timestamp":"2026-04-15T03:23:16Z","unix":1776223396,"oi":{"BTCUSDT":"0","ETHUSDT":"0","SOLUSDT":"0","XRPUSDT":"0","BNBUSDT":"0"},"oi_value":{"BTCUSDT":"0","ETHUSDT":"0","SOLUSDT":"0","XRPUSDT":"0","BNBUSDT":"0"}},{"timestamp":"2026-04-15T05:34:57Z","unix":1776231297,"oi":{"BTCUSDT":"0","ETHUSDT":"0","SOLUSDT":"0","XRPUSDT":"0","BNBUSDT":"0"},"oi_value":{"BTCUSDT":"0","ETHUSDT":"0","SOLUSDT":"0","XRPUSDT":"0","BNBUSDT":"0"}},{"timestamp":"2026-04-15T07:09:46Z","unix":1776236986,"oi":{"BTCUSDT":"0","ETHUSDT":"0","SOLUSDT":"0","XRPUSDT":"0","BNBUSDT":"0"},"oi_value":{"BTCUSDT":"0","ETHUSDT":"0","SOLUSDT":"0","XRPUSDT":"0","BNBUSDT":"0"}},{"timestamp":"2026-04-15T08:53:24Z","unix":1776243204,"oi":{"BTCUSDT":"0","ETHUSDT":"0","SOLUSDT":"0","XRPUSDT":"0","BNBUSDT":"0"},"oi_value":{"BTCUSDT":"0","ETHUSDT":"0","SOLUSDT":"0","XRPUSDT":"0","BNBUSDT":"0"}},{"timestamp":"2026-04-15T10:06:20Z","unix":1776247580,"oi":{"BTCUSDT":"0","ETHUSDT":"0","SOLUSDT":"0","XRPUSDT":"0","BNBUSDT":"0"},"oi_value":{"BTCUSDT":"0","ETHUSDT":"0","SOLUSDT":"0","XRPUSDT":"0","BNBUSDT":"0"}},{"timestamp":"2026-04-15T11:14:18Z","unix":1776251658,"oi":{"BTCUSDT":"0","ETHUSDT":"0","SOLUSDT":"0","XRPUSDT":"0","BNBUSDT":"0"},"oi_value":{"BTCUSDT":"0","ETHUSDT":"0","SOLUSDT":"0","XRPUSDT":"0","BNBUSDT":"0"}},{"timestamp":"2026-04-15T12:06:41Z","unix":1776254801,"oi":{"BTCUSDT":"0","ETHUSDT":"0","SOLUSDT":"0","XRPUSDT":"0","BNBUSDT":"0"},"oi_value":{"BTCUSDT":"0","ETHUSDT":"0","SOLUSDT":"0","XRPUSDT":"0","BNBUSDT":"0"}},{"timestamp":"2026-04-15T14:01:54Z","unix":1776261714,"oi":{"BTCUSDT":"0","ETHUSDT":"0","SOLUSDT":"0","XRPUSDT":"0","BNBUSDT":"0"},"oi_value":{"BTCUSDT":"0","ETHUSDT":"0","SOLUSDT":"0","XRPUSDT":"0","BNBUSDT":"0"}},{"timestamp":"2026-04-15T15:13:48Z","unix":1776266028,"oi":{"BTCUSDT":"0","ETHUSDT":"0","SOLUSDT":"0","XRPUSDT":"0","BNBUSDT":"0"},"oi_value":{"BTCUSDT":"0","ETHUSDT":"0","SOLUSDT":"0","XRPUSDT":"0","BNBUSDT":"0"}},{"timestamp":"2026-04-15T16:15:26Z","unix":1776269726,"oi":{"BTCUSDT":"0","ETHUSDT":"0","SOLUSDT":"0","XRPUSDT":"0","BNBUSDT":"0"},"oi_value":{"BTCUSDT":"0","ETHUSDT":"0","SOLUSDT":"0","XRPUSDT":"0","BNBUSDT":"0"}},{"timestamp":"2026-04-15T17:32:58Z","unix":1776274378,"oi":{"BTCUSDT":"0","ETHUSDT":"0","SOLUSDT":"0","XRPUSDT":"0","BNBUSDT":"0"},"oi_value":{"BTCUSDT":"0","ETHUSDT":"0","SOLUSDT":"0","XRPUSDT":"0","BNBUSDT":"0"}},{"timestamp":"2026-04-15T18:44:34Z","unix":1776278674,"oi":{"BTCUSDT":"0","ETHUSDT":"0","SOLUSDT":"0","XRPUSDT":"0","BNBUSDT":"0"},"oi_value":{"BTCUSDT":"0","ETHUSDT":"0","SOLUSDT":"0","XRPUSDT":"0","BNBUSDT":"0"}},{"timestamp":"2026-04-15T20:34:43Z","unix":1776285283,"oi":{"BTCUSDT":"0","ETHUSDT":"0","SOLUSDT":"0","XRPUSDT":"0","BNBUSDT":"0"},"oi_value":{"BTCUSDT":"0","ETHUSDT":"0","SOLUSDT":"0","XRPUSDT":"0","BNBUSDT":"0"}},{"timestamp":"2026-04-15T21:32:13Z","unix":1776288733,"oi":{"BTCUSDT":"0","ETHUSDT":"0","SOLUSDT":"0","XRPUSDT":"0","BNBUSDT":"0"},"oi_value":{"BTCUSDT":"0","ETHUSDT":"0","SOLUSDT":"0","XRPUSDT":"0","BNBUSDT":"0"}},{"timestamp":"2026-04-15T22:22:25Z","unix":1776291745,"oi":{"BTCUSDT":"0","ETHUSDT":"0","SOLUSDT":"0","XRPUSDT":"0","BNBUSDT":"0"},"oi_value":{"BTCUSDT":"0","ETHUSDT":"0","SOLUSDT":"0","XRPUSDT":"0","BNBUSDT":"0"}},{"timestamp":"2026-04-15T23:05:35Z","unix":1776294335,"oi":{"BTCUSDT":"0","ETHUSDT":"0","SOLUSDT":"0","XRPUSDT":"0","BNBUSDT":"0"},"oi_value":{"BTCUSDT":"0","ETHUSDT":"0","SOLUSDT":"0","XRPUSDT":"0","BNBUSDT":"0"}},{"timestamp":"2026-04-15T23:55:47Z","unix":1776297347,"oi":{"BTCUSDT":"0","ETHUSDT":"0","SOLUSDT":"0","XRPUSDT":"0","BNBUSDT":"0"},"oi_value":{"BTCUSDT":"0","ETHUSDT":"0","SOLUSDT":"0","XRPUSDT":"0","BNBUSDT":"0"}},{"timestamp":"2026-04-16T02:08:44Z","unix":1776305324,"oi":{"BTCUSDT":"0","ETHUSDT":"0","SOLUSDT":"0","XRPUSDT":"0","BNBUSDT":"0"},"oi_value":{"BTCUSDT":"0","ETHUSDT":"0","SOLUSDT":"0","XRPUSDT":"0","BNBUSDT":"0"}},{"timestamp":"2026-04-16T05:11:39Z","unix":1776316299,"oi":{"BTCUSDT":"0","ETHUSDT":"0","SOLUSDT":"0","XRPUSDT":"0","BNBUSDT":"0"},"oi_value":{"BTCUSDT":"0","ETHUSDT":"0","SOLUSDT":"0","XRPUSDT":"0","BNBUSDT":"0"}},{"timestamp":"2026-04-16T07:03:04Z","unix":1776322984,"oi":{"BTCUSDT":"0","ETHUSDT":"0","SOLUSDT":"0","XRPUSDT":"0","BNBUSDT":"0"},"oi_value":{"BTCUSDT":"0","ETHUSDT":"0","SOLUSDT":"0","XRPUSDT":"0","BNBUSDT":"0"}},{"timestamp":"2026-04-16T08:51:20Z","unix":1776329480,"oi":{"BTCUSDT":"0","ETHUSDT":"0","SOLUSDT":"0","XRPUSDT":"0","BNBUSDT":"0"},"oi_value":{"BTCUSDT":"0","ETHUSDT":"0","SOLUSDT":"0","XRPUSDT":"0","BNBUSDT":"0"}},{"timestamp":"2026-04-16T10:03:17Z","unix":1776333797,"oi":{"BTCUSDT":"0","ETHUSDT":"0","SOLUSDT":"0","XRPUSDT":"0","BNBUSDT":"0"},"oi_value":{"BTCUSDT":"0","ETHUSDT":"0","SOLUSDT":"0","XRPUSDT":"0","BNBUSDT":"0"}},{"timestamp":"2026-04-16T11:15:25Z","unix":1776338125,"oi":{"BTCUSDT":"0","ETHUSDT":"0","SOLUSDT":"0","XRPUSDT":"0","BNBUSDT":"0"},"oi_value":{"BTCUSDT":"0","ETHUSDT":"0","SOLUSDT":"0","XRPUSDT":"0","BNBUSDT":"0"}},{"timestamp":"2026-04-16T12:11:00Z","unix":1776341460,"oi":{"BTCUSDT":"0","ETHUSDT":"0","SOLUSDT":"0","XRPUSDT":"0","BNBUSDT":"0"},"oi_value":{"BTCUSDT":"0","ETHUSDT":"0","SOLUSDT":"0","XRPUSDT":"0","BNBUSDT":"0"}},{"timestamp":"2026-04-16T14:12:04Z","unix":1776348724,"oi":{"BTCUSDT":"0","ETHUSDT":"0","SOLUSDT":"0","XRPUSDT":"0","BNBUSDT":"0"},"oi_value":{"BTCUSDT":"0","ETHUSDT":"0","SOLUSDT":"0","XRPUSDT":"0","BNBUSDT":"0"}},{"timestamp":"2026-04-16T15:55:06Z","unix":1776354906,"oi":{"BTCUSDT":"0","ETHUSDT":"0","SOLUSDT":"0","XRPUSDT":"0","BNBUSDT":"0"},"oi_value":{"BTCUSDT":"0","ETHUSDT":"0","SOLUSDT":"0","XRPUSDT":"0","BNBUSDT":"0"}},{"timestamp":"2026-04-16T17:06:24Z","unix":1776359184,"oi":{"BTCUSDT":"0","ETHUSDT":"0","SOLUSDT":"0","XRPUSDT":"0","BNBUSDT":"0"},"oi_value":{"BTCUSDT":"0","ETHUSDT":"0","SOLUSDT":"0","XRPUSDT":"0","BNBUSDT":"0"}},{"timestamp":"2026-04-16T18:16:12Z","unix":1776363372,"oi":{"BTCUSDT":"0","ETHUSDT":"0","SOLUSDT":"0","XRPUSDT":"0","BNBUSDT":"0"},"oi_value":{"BTCUSDT":"0","ETHUSDT":"0","SOLUSDT":"0","XRPUSDT":"0","BNBUSDT":"0"}},{"timestamp":"2026-04-16T19:39:25Z","unix":1776368365,"oi":{"BTCUSDT":"0","ETHUSDT":"0","SOLUSDT":"0","XRPUSDT":"0","BNBUSDT":"0"},"oi_value":{"BTCUSDT":"0","ETHUSDT":"0","SOLUSDT":"0","XRPUSDT":"0","BNBUSDT":"0"}},{"timestamp":"2026-04-16T20:28:30Z","unix":1776371310,"oi":{"BTCUSDT":"0","ETHUSDT":"0","SOLUSDT":"0","XRPUSDT":"0","BNBUSDT":"0"},"oi_value":{"BTCUSDT":"0","ETHUSDT":"0","SOLUSDT":"0","XRPUSDT":"0","BNBUSDT":"0"}},{"timestamp":"2026-04-16T21:10:33Z","unix":1776373833,"oi":{"BTCUSDT":"0","ETHUSDT":"0","SOLUSDT":"0","XRPUSDT":"0","BNBUSDT":"0"},"oi_value":{"BTCUSDT":"0","ETHUSDT":"0","SOLUSDT":"0","XRPUSDT":"0","BNBUSDT":"0"}},{"timestamp":"2026-04-16T21:58:24Z","unix":1776376704,"oi":{"BTCUSDT":"0","ETHUSDT":"0","SOLUSDT":"0","XRPUSDT":"0","BNBUSDT":"0"},"oi_value":{"BTCUSDT":"0","ETHUSDT":"0","SOLUSDT":"0","XRPUSDT":"0","BNBUSDT":"0"}},{"timestamp":"2026-04-16T22:42:33Z","unix":1776379353,"oi":{"BTCUSDT":"0","ETHUSDT":"0","SOLUSDT":"0","XRPUSDT":"0","BNBUSDT":"0"},"oi_value":{"BTCUSDT":"0","ETHUSDT":"0","SOLUSDT":"0","XRPUSDT":"0","BNBUSDT":"0"}},{"timestamp":"2026-04-16T23:25:51Z","unix":1776381951,"oi":{"BTCUSDT":"0","ETHUSDT":"0","SOLUSDT":"0","XRPUSDT":"0","BNBUSDT":"0"},"oi_value":{"BTCUSDT":"0","ETHUSDT":"0","SOLUSDT":"0","XRPUSDT":"0","BNBUSDT":"0"}},{"timestamp":"2026-04-17T00:03:40Z","unix":1776384220,"oi":{"BTCUSDT":"0","ETHUSDT":"0","SOLUSDT":"0","XRPUSDT":"0","BNBUSDT":"0"},"oi_value":{"BTCUSDT":"0","ETHUSDT":"0","SOLUSDT":"0","XRPUSDT":"0","BNBUSDT":"0"}},{"timestamp":"2026-04-17T03:37:43Z","unix":1776397063,"oi":{"BTCUSDT":"0","ETHUSDT":"0","SOLUSDT":"0","XRPUSDT":"0","BNBUSDT":"0"},"oi_value":{"BTCUSDT":"0","ETHUSDT":"0","SOLUSDT":"0","XRPUSDT":"0","BNBUSDT":"0"}},{"timestamp":"2026-04-17T05:51:05Z","unix":1776405065,"oi":{"BTCUSDT":"0","ETHUSDT":"0","SOLUSDT":"0","XRPUSDT":"0","BNBUSDT":"0"},"oi_value":{"BTCUSDT":"0","ETHUSDT":"0","SOLUSDT":"0","XRPUSDT":"0","BNBUSDT":"0"}},{"timestamp":"2026-04-17T07:14:44Z","unix":1776410084,"oi":{"BTCUSDT":"0","ETHUSDT":"0","SOLUSDT":"0","XRPUSDT":"0","BNBUSDT":"0"},"oi_value":{"BTCUSDT":"0","ETHUSDT":"0","SOLUSDT":"0","XRPUSDT":"0","BNBUSDT":"0"}},{"timestamp":"2026-04-17T08:56:02Z","unix":1776416162,"oi":{"BTCUSDT":"0","ETHUSDT":"0","SOLUSDT":"0","XRPUSDT":"0","BNBUSDT":"0"},"oi_value":{"BTCUSDT":"0","ETHUSDT":"0","SOLUSDT":"0","XRPUSDT":"0","BNBUSDT":"0"}},{"timestamp":"2026-04-17T10:10:49Z","unix":1776420649,"oi":{"BTCUSDT":"0","ETHUSDT":"0","SOLUSDT":"0","XRPUSDT":"0","BNBUSDT":"0"},"oi_value":{"BTCUSDT":"0","ETHUSDT":"0","SOLUSDT":"0","XRPUSDT":"0","BNBUSDT":"0"}},{"timestamp":"2026-04-17T11:12:38Z","unix":1776424358,"oi":{"BTCUSDT":"0","ETHUSDT":"0","SOLUSDT":"0","XRPUSDT":"0","BNBUSDT":"0"},"oi_value":{"BTCUSDT":"0","ETHUSDT":"0","SOLUSDT":"0","XRPUSDT":"0","BNBUSDT":"0"}},{"timestamp":"2026-04-17T12:04:14Z","unix":1776427454,"oi":{"BTCUSDT":"0","ETHUSDT":"0","SOLUSDT":"0","XRPUSDT":"0","BNBUSDT":"0"},"oi_value":{"BTCUSDT":"0","ETHUSDT":"0","SOLUSDT":"0","XRPUSDT":"0","BNBUSDT":"0"}},{"timestamp":"2026-04-17T13:54:17Z","unix":1776434057,"oi":{"BTCUSDT":"0","ETHUSDT":"0","SOLUSDT":"0","XRPUSDT":"0","BNBUSDT":"0"},"oi_value":{"BTCUSDT":"0","ETHUSDT":"0","SOLUSDT":"0","XRPUSDT":"0","BNBUSDT":"0"}},{"timestamp":"2026-04-17T14:48:01Z","unix":1776437281,"oi":{"BTCUSDT":"0","ETHUSDT":"0","SOLUSDT":"0","XRPUSDT":"0","BNBUSDT":"0"},"oi_value":{"BTCUSDT":"0","ETHUSDT":"0","SOLUSDT":"0","XRPUSDT":"0","BNBUSDT":"0"}},{"timestamp":"2026-04-17T15:44:31Z","unix":1776440671,"oi":{"BTCUSDT":"0","ETHUSDT":"0","SOLUSDT":"0","XRPUSDT":"0","BNBUSDT":"0"},"oi_value":{"BTCUSDT":"0","ETHUSDT":"0","SOLUSDT":"0","XRPUSDT":"0","BNBUSDT":"0"}},{"timestamp":"2026-04-17T16:37:03Z","unix":1776443823,"oi":{"BTCUSDT":"0","ETHUSDT":"0","SOLUSDT":"0","XRPUSDT":"0","BNBUSDT":"0"},"oi_value":{"BTCUSDT":"0","ETHUSDT":"0","SOLUSDT":"0","XRPUSDT":"0","BNBUSDT":"0"}},{"timestamp":"2026-04-17T17:29:55Z","unix":1776446995,"oi":{"BTCUSDT":"0","ETHUSDT":"0","SOLUSDT":"0","XRPUSDT":"0","BNBUSDT":"0"},"oi_value":{"BTCUSDT":"0","ETHUSDT":"0","SOLUSDT":"0","XRPUSDT":"0","BNBUSDT":"0"}},{"timestamp":"2026-04-17T18:29:48Z","unix":1776450588,"oi":{"BTCUSDT":"0","ETHUSDT":"0","SOLUSDT":"0","XRPUSDT":"0","BNBUSDT":"0"},"oi_value":{"BTCUSDT":"0","ETHUSDT":"0","SOLUSDT":"0","XRPUSDT":"0","BNBUSDT":"0"}},{"timestamp":"2026-04-17T19:39:11Z","unix":1776454751,"oi":{"BTCUSDT":"0","ETHUSDT":"0","SOLUSDT":"0","XRPUSDT":"0","BNBUSDT":"0"},"oi_value":{"BTCUSDT":"0","ETHUSDT":"0","SOLUSDT":"0","XRPUSDT":"0","BNBUSDT":"0"}},{"timestamp":"2026-04-17T20:24:35Z","unix":1776457475,"oi":{"BTCUSDT":"0","ETHUSDT":"0","SOLUSDT":"0","XRPUSDT":"0","BNBUSDT":"0"},"oi_value":{"BTCUSDT":"0","ETHUSDT":"0","SOLUSDT":"0","XRPUSDT":"0","BNBUSDT":"0"}},{"timestamp":"2026-04-17T21:07:37Z","unix":1776460057,"oi":{"BTCUSDT":"0","ETHUSDT":"0","SOLUSDT":"0","XRPUSDT":"0","BNBUSDT":"0"},"oi_value":{"BTCUSDT":"0","ETHUSDT":"0","SOLUSDT":"0","XRPUSDT":"0","BNBUSDT":"0"}},{"timestamp":"2026-04-17T21:58:08Z","unix":1776463088,"oi":{"BTCUSDT":"0","ETHUSDT":"0","SOLUSDT":"0","XRPUSDT":"0","BNBUSDT":"0"},"oi_value":{"BTCUSDT":"0","ETHUSDT":"0","SOLUSDT":"0","XRPUSDT":"0","BNBUSDT":"0"}},{"timestamp":"2026-04-17T22:40:43Z","unix":1776465643,"oi":{"BTCUSDT":"0","ETHUSDT":"0","SOLUSDT":"0","XRPUSDT":"0","BNBUSDT":"0"},"oi_value":{"BTCUSDT":"0","ETHUSDT":"0","SOLUSDT":"0","XRPUSDT":"0","BNBUSDT":"0"}},{"timestamp":"2026-04-17T23:23:50Z","unix":1776468230,"oi":{"BTCUSDT":"0","ETHUSDT":"0","SOLUSDT":"0","XRPUSDT":"0","BNBUSDT":"0"},"oi_value":{"BTCUSDT":"0","ETHUSDT":"0","SOLUSDT":"0","XRPUSDT":"0","BNBUSDT":"0"}},{"timestamp":"2026-04-18T00:00:15Z","unix":1776470415,"oi":{"BTCUSDT":"0","ETHUSDT":"0","SOLUSDT":"0","XRPUSDT":"0","BNBUSDT":"0"},"oi_value":{"BTCUSDT":"0","ETHUSDT":"0","SOLUSDT":"0","XRPUSDT":"0","BNBUSDT":"0"}},{"timestamp":"2026-04-18T03:18:04Z","unix":1776482284,"oi":{"BTCUSDT":"0","ETHUSDT":"0","SOLUSDT":"0","XRPUSDT":"0","BNBUSDT":"0"},"oi_value":{"BTCUSDT":"0","ETHUSDT":"0","SOLUSDT":"0","XRPUSDT":"0","BNBUSDT":"0"}},{"timestamp":"2026-04-18T05:18:59Z","unix":1776489539,"oi":{"BTCUSDT":"0","ETHUSDT":"0","SOLUSDT":"0","XRPUSDT":"0","BNBUSDT":"0"},"oi_value":{"BTCUSDT":"0","ETHUSDT":"0","SOLUSDT":"0","XRPUSDT":"0","BNBUSDT":"0"}},{"timestamp":"2026-04-18T06:40:24Z","unix":1776494424,"oi":{"BTCUSDT":"0","ETHUSDT":"0","SOLUSDT":"0","XRPUSDT":"0","BNBUSDT":"0"},"oi_value":{"BTCUSDT":"0","ETHUSDT":"0","SOLUSDT":"0","XRPUSDT":"0","BNBUSDT":"0"}},{"timestamp":"2026-04-18T07:44:32Z","unix":1776498272,"oi":{"BTCUSDT":"0","ETHUSDT":"0","SOLUSDT":"0","XRPUSDT":"0","BNBUSDT":"0"},"oi_value":{"BTCUSDT":"0","ETHUSDT":"0","SOLUSDT":"0","XRPUSDT":"0","BNBUSDT":"0"}},{"timestamp":"2026-04-18T09:24:47Z","unix":1776504287,"oi":{"BTCUSDT":"0","ETHUSDT":"0","SOLUSDT":"0","XRPUSDT":"0","BNBUSDT":"0"},"oi_value":{"BTCUSDT":"0","ETHUSDT":"0","SOLUSDT":"0","XRPUSDT":"0","BNBUSDT":"0"}},{"timestamp":"2026-04-18T10:05:24Z","unix":1776506724,"oi":{"BTCUSDT":"0","ETHUSDT":"0","SOLUSDT":"0","XRPUSDT":"0","BNBUSDT":"0"},"oi_value":{"BTCUSDT":"0","ETHUSDT":"0","SOLUSDT":"0","XRPUSDT":"0","BNBUSDT":"0"}},{"timestamp":"2026-04-18T10:56:26Z","unix":1776509786,"oi":{"BTCUSDT":"0","ETHUSDT":"0","SOLUSDT":"0","XRPUSDT":"0","BNBUSDT":"0"},"oi_value":{"BTCUSDT":"0","ETHUSDT":"0","SOLUSDT":"0","XRPUSDT":"0","BNBUSDT":"0"}},{"timestamp":"2026-04-18T11:32:17Z","unix":1776511937,"oi":{"BTCUSDT":"0","ETHUSDT":"0","SOLUSDT":"0","XRPUSDT":"0","BNBUSDT":"0"},"oi_value":{"BTCUSDT":"0","ETHUSDT":"0","SOLUSDT":"0","XRPUSDT":"0","BNBUSDT":"0"}},{"timestamp":"2026-04-18T12:00:56Z","unix":1776513656,"oi":{"BTCUSDT":"0","ETHUSDT":"0","SOLUSDT":"0","XRPUSDT":"0","BNBUSDT":"0"},"oi_value":{"BTCUSDT":"0","ETHUSDT":"0","SOLUSDT":"0","XRPUSDT":"0","BNBUSDT":"0"}},{"timestamp":"2026-04-18T13:20:35Z","unix":1776518435,"oi":{"BTCUSDT":"0","ETHUSDT":"0","SOLUSDT":"0","XRPUSDT":"0","BNBUSDT":"0"},"oi_value":{"BTCUSDT":"0","ETHUSDT":"0","SOLUSDT":"0","XRPUSDT":"0","BNBUSDT":"0"}},{"timestamp":"2026-04-18T14:07:27Z","unix":1776521247,"oi":{"BTCUSDT":"0","ETHUSDT":"0","SOLUSDT":"0","XRPUSDT":"0","BNBUSDT":"0"},"oi_value":{"BTCUSDT":"0","ETHUSDT":"0","SOLUSDT":"0","XRPUSDT":"0","BNBUSDT":"0"}},{"timestamp":"2026-04-18T14:55:53Z","unix":1776524153,"oi":{"BTCUSDT":"0","ETHUSDT":"0","SOLUSDT":"0","XRPUSDT":"0","BNBUSDT":"0"},"oi_value":{"BTCUSDT":"0","ETHUSDT":"0","SOLUSDT":"0","XRPUSDT":"0","BNBUSDT":"0"}},{"timestamp":"2026-04-18T15:33:48Z","unix":1776526428,"oi":{"BTCUSDT":"0","ETHUSDT":"0","SOLUSDT":"0","XRPUSDT":"0","BNBUSDT":"0"},"oi_value":{"BTCUSDT":"0","ETHUSDT":"0","SOLUSDT":"0","XRPUSDT":"0","BNBUSDT":"0"}},{"timestamp":"2026-04-18T16:05:02Z","unix":1776528302,"oi":{"BTCUSDT":"0","ETHUSDT":"0","SOLUSDT":"0","XRPUSDT":"0","BNBUSDT":"0"},"oi_value":{"BTCUSDT":"0","ETHUSDT":"0","SOLUSDT":"0","XRPUSDT":"0","BNBUSDT":"0"}},{"timestamp":"2026-04-18T16:55:26Z","unix":1776531326,"oi":{"BTCUSDT":"0","ETHUSDT":"0","SOLUSDT":"0","XRPUSDT":"0","BNBUSDT":"0"},"oi_value":{"BTCUSDT":"0","ETHUSDT":"0","SOLUSDT":"0","XRPUSDT":"0","BNBUSDT":"0"}},{"timestamp":"2026-04-18T17:31:38Z","unix":1776533498,"oi":{"BTCUSDT":"0","ETHUSDT":"0","SOLUSDT":"0","XRPUSDT":"0","BNBUSDT":"0"},"oi_value":{"BTCUSDT":"0","ETHUSDT":"0","SOLUSDT":"0","XRPUSDT":"0","BNBUSDT":"0"}},{"timestamp":"2026-04-18T18:04:55Z","unix":1776535495,"oi":{"BTCUSDT":"0","ETHUSDT":"0","SOLUSDT":"0","XRPUSDT":"0","BNBUSDT":"0"},"oi_value":{"BTCUSDT":"0","ETHUSDT":"0","SOLUSDT":"0","XRPUSDT":"0","BNBUSDT":"0"}},{"timestamp":"2026-04-18T19:49:29Z","unix":1776541769,"oi":{"BTCUSDT":"0","ETHUSDT":"0","SOLUSDT":"0","XRPUSDT":"0","BNBUSDT":"0"},"oi_value":{"BTCUSDT":"0","ETHUSDT":"0","SOLUSDT":"0","XRPUSDT":"0","BNBUSDT":"0"}},{"timestamp":"2026-04-18T20:20:12Z","unix":1776543612,"oi":{"BTCUSDT":"0","ETHUSDT":"0","SOLUSDT":"0","XRPUSDT":"0","BNBUSDT":"0"},"oi_value":{"BTCUSDT":"0","ETHUSDT":"0","SOLUSDT":"0","XRPUSDT":"0","BNBUSDT":"0"}},{"timestamp":"2026-04-18T20:57:21Z","unix":1776545841,"oi":{"BTCUSDT":"0","ETHUSDT":"0","SOLUSDT":"0","XRPUSDT":"0","BNBUSDT":"0"},"oi_value":{"BTCUSDT":"0","ETHUSDT":"0","SOLUSDT":"0","XRPUSDT":"0","BNBUSDT":"0"}},{"timestamp":"2026-04-18T21:34:42Z","unix":1776548082,"oi":{"BTCUSDT":"0","ETHUSDT":"0","SOLUSDT":"0","XRPUSDT":"0","BNBUSDT":"0"},"oi_value":{"BTCUSDT":"0","ETHUSDT":"0","SOLUSDT":"0","XRPUSDT":"0","BNBUSDT":"0"}},{"timestamp":"2026-04-18T22:02:07Z","unix":1776549727,"oi":{"BTCUSDT":"0","ETHUSDT":"0","SOLUSDT":"0","XRPUSDT":"0","BNBUSDT":"0"},"oi_value":{"BTCUSDT":"0","ETHUSDT":"0","SOLUSDT":"0","XRPUSDT":"0","BNBUSDT":"0"}},{"timestamp":"2026-04-18T22:48:26Z","unix":1776552506,"oi":{"BTCUSDT":"0","ETHUSDT":"0","SOLUSDT":"0","XRPUSDT":"0","BNBUSDT":"0"},"oi_value":{"BTCUSDT":"0","ETHUSDT":"0","SOLUSDT":"0","XRPUSDT":"0","BNBUSDT":"0"}},{"timestamp":"2026-04-18T23:21:25Z","unix":1776554485,"oi":{"BTCUSDT":"0","ETHUSDT":"0","SOLUSDT":"0","XRPUSDT":"0","BNBUSDT":"0"},"oi_value":{"BTCUSDT":"0","ETHUSDT":"0","SOLUSDT":"0","XRPUSDT":"0","BNBUSDT":"0"}}]